dyn/__init__.py
dyn/compat.py
dyn/core.py
dyn/encrypt.py
dyn/mm/__init__.py
dyn/mm/accounts.py
dyn/mm/errors.py
dyn/mm/message.py
dyn/mm/reports.py
dyn/mm/session.py
dyn/mm/utils.py
dyn/tm/__init__.py
dyn/tm/accounts.py
dyn/tm/errors.py
dyn/tm/records.py
dyn/tm/reports.py
dyn/tm/session.py
dyn/tm/task.py
dyn/tm/tools.py
dyn/tm/utils.py
dyn/tm/zones.py
dyn/tm/services/__init__.py
dyn/tm/services/active_failover.py
dyn/tm/services/advanced_redirect.py
dyn/tm/services/ddns.py
dyn/tm/services/dnssec.py
dyn/tm/services/dsf.py
dyn/tm/services/geo.py
dyn/tm/services/gslb.py
dyn/tm/services/httpredirect.py
dyn/tm/services/reversedns.py
dyn/tm/services/rttm.py
dyn-1.8.0.dist-info/DESCRIPTION.rst
dyn-1.8.0.dist-info/METADATA
dyn-1.8.0.dist-info/RECORD
dyn-1.8.0.dist-info/WHEEL
dyn-1.8.0.dist-info/metadata.json
dyn-1.8.0.dist-info/top_level.txt
