Metadata-Version: 2.0
Name: dyn
Version: 1.8.0
Summary: Dyn REST API wrapper
Home-page: https://github.com/dyninc/dyn-python
Author: Jonathan Nappi, Cole Tuininga
Author-email: jnappi@dyn.com
License: UNKNOWN
Keywords: dyn,api,dns,email,dyndns,dynemail
Platform: UNKNOWN
Classifier: Programming Language :: Python :: 2
Classifier: Programming Language :: Python :: 3
Classifier: Topic :: Internet :: Name Service (DNS)
Classifier: Topic :: Software Development :: Libraries
